LICENSE
README.md
setup.py
bin/wfs_html.py
bin/wms_html.py
fmiopendata/__init__.py
fmiopendata/grid.py
fmiopendata/lightning.py
fmiopendata/multipoint.py
fmiopendata/multipoint_vara.py
fmiopendata/radar.py
fmiopendata/sounding.py
fmiopendata/utils.py
fmiopendata/wfs.py
fmiopendata/wms.py
fmiopendata.egg-info/PKG-INFO
fmiopendata.egg-info/SOURCES.txt
fmiopendata.egg-info/dependency_links.txt
fmiopendata.egg-info/requires.txt
fmiopendata.egg-info/top_level.txt