Metadata-Version: 2.1
Name: fmiopendata
Version: 0.4.1
Summary: Python library for accessing FMI open data
Home-page: https://github.com/pnuu/pyfmiopendata
Author: Panu Lahtinen
Author-email: pnuu+git@iki.fi
Classifier: Development Status :: 4 - Beta
Classifier: Intended Audience :: Science/Research
Classifier: License :: OSI Approved :: GNU General Public License v3 or later (GPLv3+)
Classifier: Operating System :: OS Independent
Classifier: Programming Language :: Python
Classifier: Topic :: Scientific/Engineering
Requires-Python: >=3.8
Provides-Extra: radar
Provides-Extra: grid
Provides-Extra: all
License-File: LICENSE
